wagtailmeili/.DS_Store
wagtailmeili/__init__.py
wagtailmeili/apps.py
wagtailmeili/backend.py
wagtailmeili/exceptions.py
wagtailmeili/index.py
wagtailmeili/manager.py
wagtailmeili/paginator.py
wagtailmeili/query_compiler.py
wagtailmeili/rebuilder.py
wagtailmeili/results.py
wagtailmeili/settings.py
wagtailmeili/signals.py
wagtailmeili/utils.py
wagtailmeili/version.py
wagtailmeili/management/commands/cleanup_search_index.py
wagtailmeili/management/commands/meilisearch_delete_all_indexes.py
wagtailmeili/templatetags/meilisearch.py
wagtailmeili-0.5.2.dist-info/licenses/LICENSE
wagtailmeili-0.5.2.dist-info/WHEEL
wagtailmeili-0.5.2.dist-info/METADATA
wagtailmeili-0.5.2.dist-info/RECORD
