Metadata-Version: 2.4
Name: wagtailmeili
Version: 0.5.2
Summary: A Meilisearch backend for Wagtail CMS
Keywords: wagtail,django,search,meilisearch,backend
Author-email: Maxime Decooman <maxime@softquantum.com>
Maintainer-email: Maxime Decooman <maxime@softquantum.com>
Requires-Python: >=3.11
Classifier: Development Status :: 4 - Beta
Classifier: Environment :: Web Environment
Classifier: Framework :: Django
Classifier: Framework :: Wagtail
Classifier: Framework :: Wagtail :: 5
Classifier: Framework :: Wagtail :: 6
Classifier: Framework :: Wagtail :: 7
Classifier: Intended Audience :: Developers
Classifier: License :: OSI Approved :: BSD License
Classifier: Operating System :: OS Independent
Classifier: Programming Language :: Python :: 3
Classifier: Programming Language :: Python :: 3.11
Classifier: Programming Language :: Python :: 3.12
Classifier: Programming Language :: Python :: 3.13
Classifier: Programming Language :: Python :: 3.14
Classifier: Topic :: Internet :: WWW/HTTP :: Indexing/Search
License-File: LICENSE
Requires-Dist: wagtail>=5.2
Requires-Dist: meilisearch>=0.29
Requires-Dist: python-decouple>=3.8
Project-URL: Home, https://github.com/softquantum/wagtailmeili
Project-URL: Issues, https://github.com/softquantum/wagtailmeili/issues
